hku_diabetes/__init__.py
hku_diabetes/analytics.py
hku_diabetes/config.py
hku_diabetes/importer.py
hku_diabetes/plot.py
tests/__init__.py
tests/test_analytics.py
tests/test_importer.py
hku_diabetes-0.0.2.dist-info/LICENSE
hku_diabetes-0.0.2.dist-info/METADATA
hku_diabetes-0.0.2.dist-info/WHEEL
hku_diabetes-0.0.2.dist-info/top_level.txt
hku_diabetes-0.0.2.dist-info/RECORD
