Metadata-Version: 2.1
Name: hku-diabetes
Version: 0.0.2
Summary: HKU Diabetes Data Anlytics
Home-page: https://github.com/luithw/hku_diabetes
Author: Tim Lui
Author-email: lui.thw@cantab.net
License: MIT
Download-URL: https://github.com/luithw/hku_diabetes/tarball/0.0.1
Platform: UNKNOWN
Classifier: Development Status :: 3 - Alpha
Classifier: Intended Audience :: Science/Research
Classifier: License :: OSI Approved :: MIT License
Classifier: Programming Language :: Python :: 3.6
Classifier: Topic :: Software Development :: Libraries
Classifier: Topic :: Software Development :: Libraries :: Python Modules
Requires-Dist: lxml (>=4.2.5)
Requires-Dist: matplotlib (>=3.0.0)
Requires-Dist: numpy (>=1.15.2)
Requires-Dist: pandas (>=0.23.4)
Requires-Dist: scipy (>=1.1.0)
Requires-Dist: six (>=1.9.0)
Requires-Dist: xlrd (>=1.1.0)
Provides-Extra: tests
Requires-Dist: pytest; extra == 'tests'
